HOS_ME/__init__.py
HOS_ME/__main__.py
HOS_ME/app.py
HOS_ME/cli/__init__.py
HOS_ME/cli/base.py
HOS_ME/cli/registry.py
HOS_ME/commands/__init__.py
HOS_ME/commands/approval.py
HOS_ME/commands/custom.py
HOS_ME/commands/meeting.py
HOS_ME/commands/ollama.py
HOS_ME/commands/project.py
HOS_ME/commands/rag.py
HOS_ME/commands/report.py
HOS_ME/commands/schedule.py
HOS_ME/commands/task.py
HOS_ME/commands/template.py
HOS_ME/static/css/style.css
HOS_ME/static/js/app.js
HOS_ME/static/js/image-upload.js
HOS_ME/static/js/prompt-validation.js
HOS_ME/templates/index.html
HOS_ME/utils/api_client.py
HOS_ME/utils/approval_manager.py
HOS_ME/utils/ascii_image_converter.py
HOS_ME/utils/batch_processor.py
HOS_ME/utils/complex_template_renderer.py
HOS_ME/utils/document_converter.py
HOS_ME/utils/docx_template_parser.py
HOS_ME/utils/file_manager.py
HOS_ME/utils/i18n.py
HOS_ME/utils/knowledge_base.py
HOS_ME/utils/kroki_renderer.py
HOS_ME/utils/meeting_manager.py
HOS_ME/utils/ocr_processor.py
HOS_ME/utils/ollama_manager.py
HOS_ME/utils/project_manager.py
HOS_ME/utils/report_generator.py
HOS_ME/utils/schedule_manager.py
HOS_ME/utils/task_manager.py
HOS_ME/utils/template_manager.py
hos_me-1.1.6.data/data/config/index.html
hos_me-1.1.6.dist-info/METADATA
hos_me-1.1.6.dist-info/WHEEL
hos_me-1.1.6.dist-info/entry_points.txt
hos_me-1.1.6.dist-info/top_level.txt
hos_me-1.1.6.dist-info/RECORD
