Metadata-Version: 2.4
Name: HOS_ME
Version: 1.1.6
Summary: HOS ME - 一个功能强大的办公自动化平台，支持批量任务处理、模板管理、复杂内容渲染和文档导入导出
Home-page: https://github.com/hos-me/hos-me
Author: HOS ME Team
Author-email: hos_me@example.com
License: MIT
Classifier: Development Status :: 5 - Production/Stable
Classifier: Intended Audience :: Developers
Classifier: Intended Audience :: System Administrators
Classifier: Topic :: Office/Business
Classifier: Topic :: Software Development :: Libraries :: Python Modules
Classifier: Programming Language :: Python :: 3
Classifier: Programming Language :: Python :: 3.7
Classifier: Programming Language :: Python :: 3.8
Classifier: Programming Language :: Python :: 3.9
Classifier: Programming Language :: Python :: 3.10
Classifier: Programming Language :: Python :: 3.11
Classifier: Framework :: Flask
Classifier: Operating System :: OS Independent
Requires-Python: >=3.7
Requires-Dist: Flask>=2.0.0
Requires-Dist: requests>=2.25.0
Requires-Dist: python-dotenv>=0.20.0
Requires-Dist: python-docx>=1.0.0
Requires-Dist: lxml>=4.6.0
Requires-Dist: pillow>=8.0.0
Requires-Dist: flask-dropzone>=2.0.0
Requires-Dist: flask-uploads>=0.2.1
Requires-Dist: click>=8.0.0
Requires-Dist: PyPDF2>=2.0.0
Requires-Dist: openpyxl>=3.0.7
Requires-Dist: pandas>=1.3.0
Requires-Dist: sqlalchemy>=2.0.0
Requires-Dist: flask-wtf>=1.1.0
Requires-Dist: flask-login>=0.6.2
Requires-Dist: flask-principal>=0.4.0
Requires-Dist: redis>=4.0.0
Requires-Dist: flask-caching>=2.0.0
Requires-Dist: celery>=5.0.0
Provides-Extra: dev
Requires-Dist: pytest>=7.0; extra == "dev"
Requires-Dist: flake8>=4.0; extra == "dev"
Requires-Dist: black>=22.0; extra == "dev"
Requires-Dist: isort>=5.0; extra == "dev"
Requires-Dist: sphinx>=4.0; extra == "dev"
Requires-Dist: sphinx_rtd_theme>=1.0; extra == "dev"
Provides-Extra: full
Requires-Dist: PyPDF2>=2.0.0; extra == "full"
Requires-Dist: openpyxl>=3.0.7; extra == "full"
Requires-Dist: pandas>=1.3.0; extra == "full"
Requires-Dist: redis>=4.0.0; extra == "full"
Requires-Dist: celery>=5.0.0; extra == "full"
Requires-Dist: python-daemon>=2.3.0; extra == "full"
Requires-Dist: click>=8.0.0; extra == "full"
Requires-Dist: python-json-logger>=2.0.0; extra == "full"
Provides-Extra: logging
Requires-Dist: python-json-logger>=2.0.0; extra == "logging"
Dynamic: author
Dynamic: author-email
Dynamic: classifier
Dynamic: description
Dynamic: description-content-type
Dynamic: home-page
Dynamic: license
Dynamic: provides-extra
Dynamic: requires-dist
Dynamic: requires-python
Dynamic: summary
